{
  "ar": {
    "channel": "/yutai-teahouse/ar",
    "title": "مقهى يوتاي",
    "lang_name": "العربية",
    "notice": "اضغط على Enter لبدء سطر جديد، اضغط على Ctrl+Enter أو انقر هنا لإرسال رسالتك",
    "online-peers": "الأقران المتصلون: ",
    "peers-found": "تم العثور على أقران، ابدأ الدردشة!",
    "posted-at": "نشر في: ",
    "preview-init": "سيتم عرض معاينة رسالتك هنا.",
    "start": "بدء تشغيل لبدء النواة Libp2p...",
    "waiting": "تم بدء نواة Libp2p، في انتظار اتصال الأقران..."
  },
  "da": {
    "channel": "/yutai-teahouse/da",
    "title": "Yutai Teahouse",
    "lang_name": "Dansk",
    "notice": "Tryk Enter for at starte en ny linje, tryk Ctrl+Enter eller klik her for at sende din besked",
    "online-peers": "Online peers: ",
    "peers-found": "Peers fundet, start med at chatte!",
    "posted-at": "Postet den: ",
    "preview-init": "Din besked vil blive vist her.",
    "start": "Starter Libp2p kerne...",
    "waiting": "Libp2p kerne startet, venter på peers..."
  },
  "de": {
    "channel": "/yutai-teahouse/de",
    "title": "Yutai Teahouse",
    "lang_name": "Deutsch",
    "notice": "Drücke Enter um eine neue Zeile zu beginnen, drücke Ctrl+Enter oder klicke hier um deine Nachricht zu senden",
    "online-peers": "Online Peers: ",
    "peers-found": "Peers gefunden, starte zu chatten!",
    "posted-at": "Geschrieben am: ",
    "preview-init": "Hier wird eine Vorschau deiner Nachricht angezeigt.",
    "start": "Starte Libp2p Kern...",
    "waiting": "Libp2p Kern gestartet, warte auf Peers..."
  },
  "el": {
    "channel": "/yutai-teahouse/el",
    "title": "Yutai Teahouse",
    "lang_name": "Ελληνικά",
    "notice": "Πατήστε Enter για να ξεκινήσετε μια νέα γραμμή, πατήστε Ctrl+Enter ή κάντε κλικ εδώ για να στείλετε το μήνυμά σας",
    "online-peers": "Συνδεδεμένοι χρήστες: ",
    "peers-found": "Βρέθηκαν χρήστες, ξεκινήστε τη συνομιλία!",
    "posted-at": "Δημοσιεύτηκε στις: ",
    "preview-init": "Η προεπισκόπηση του μηνύματός σας θα εμφανιστεί εδώ.",
    "start": "Εκκίνηση πυρήνα Libp2p...",
    "waiting": "Ο πυρήνας Libp2p ξεκίνησε, περιμένοντας σύνδεση χρηστών..."
  },
  "en-US": {
    "channel": "/yutai-teahouse/en-US",
    "title": "Yutai Teahouse",
    "lang_name": "English",
    "notice": "Press Enter to start a new line, press Ctrl+Enter or click here to send your message",
    "online-peers": "Online peers: ",
    "peers-found": "Peers found, start chatting!",
    "posted-at": "Posted at: ",
    "preview-init": "Your message preview will be shown here.",
    "start": "Starting Libp2p core...",
    "waiting": "Libp2p core started, waiting for peers to connect..."
  },
  "eo": {
    "channel": "/yutai-teahouse/eo",
    "title": "Yutai Teahouse",
    "lang_name": "Esperanto",
    "notice": "Premu Enirejon por komenci novan linion, premu Ctrl+Enirejon aŭ klaku ĉi tie por sendi vian mesaĝon",
    "online-peers": "Rete aldonitaj uzantoj: ",
    "peers-found": "Aldonitaj uzantoj, komencu babili!",
    "posted-at": "Afiŝita je: ",
    "preview-init": "Via mesaĝo aperos ĉi tie.",
    "start": "Komencante Libp2p kerno...",
    "waiting": "Libp2p kerno komencita, atendante konektojn..."
  },
  "es": {
    "channel": "/yutai-teahouse/es",
    "title": "Yutai Teahouse",
    "lang_name": "Español",
    "notice": "Presiona Enter para comenzar una nueva línea, presiona Ctrl+Enter o haz clic aquí para enviar tu mensaje",
    "online-peers": "Usuarios en línea: ",
    "peers-found": "Usuarios encontrados, ¡comienza a chatear!",
    "posted-at": "Publicado en: ",
    "preview-init": "Tu mensaje se mostrará aquí.",
    "start": "Iniciando núcleo Libp2p...",
    "waiting": "Núcleo Libp2p iniciado, esperando a que los usuarios se conecten..."
  },
  "fr": {
    "channel": "/yutai-teahouse/fr",
    "title": "Yutai Teahouse",
    "lang_name": "Français",
    "notice": "Appuyez sur Entrée pour commencer une nouvelle ligne, appuyez sur Ctrl+Entrée ou cliquez ici pour envoyer votre message",
    "online-peers": "Utilisateurs en ligne: ",
    "peers-found": "Utilisateurs trouvés, commencez à chatter!",
    "posted-at": "Posté à: ",
    "preview-init": "Votre message sera affiché ici.",
    "start": "Démarrage du noyau Libp2p...",
    "waiting": "Noyau Libp2p démarré, en attente de connexions..."
  },
  "he": {
    "channel": "/yutai-teahouse/he",
    "title": "Yutai Teahouse",
    "lang_name": "עברית",
    "notice": "לחץ על Enter כדי להתחיל שורה חדשה, לחץ על Ctrl+Enter או לחץ כאן כדי לשלוח את ההודעה שלך",
    "online-peers": "משתמשים מחוברים: ",
    "peers-found": "משתמשים נמצאו, התחל לשוחח!",
    "posted-at": "פורסם בתאריך: ",
    "preview-init": "ההודעה שלך תוצג כאן.",
    "start": "מתחיל להפעיל את ליבת Libp2p...",
    "waiting": "ליבת Libp2p הופעלה, ממתין לחיבורים..."
  },
  "hi": {
    "channel": "/yutai-teahouse/hi",
    "title": "Yutai Teahouse",
    "lang_name": "हिन्दी",
    "notice": "नई पंक्ति शुरू करने के लिए एंटर दबाएं, अपना संदेश भेजने के लिए Ctrl+Enter दबाएं या यहां क्लिक करें",
    "online-peers": "ऑनलाइन उपयोगकर्ता: ",
    "peers-found": "उपयोगकर्ता मिले, चैटिंग शुरू करें!",
    "posted-at": "पोस्ट किया गया: ",
    "preview-init": "आपका संदेश यहां दिखाया जाएगा।",
    "start": "Libp2p कोर शुरू हो रहा है...",
    "waiting": "Libp2p कोर शुरू हो गया है, उपयोगकर्ताओं के कनेक्शन की प्रतीक्षा कर रहा है..."
  },
  "it": {
    "channel": "/yutai-teahouse/it",
    "title": "Yutai Teahouse",
    "lang_name": "Italiano",
    "notice": "Premi Invio per iniziare una nuova riga, premi Ctrl+Invio o clicca qui per inviare il tuo messaggio",
    "online-peers": "Utenti online: ",
    "peers-found": "Utenti trovati, inizia a chattare!",
    "posted-at": "Pubblicato il: ",
    "preview-init": "Il tuo messaggio verrà mostrato qui.",
    "start": "Avvio del core Libp2p...",
    "waiting": "Core Libp2p avviato, in attesa di connessioni..."
  },
  "ja": {
    "channel": "/yutai-teahouse/ja",
    "title": "Yutai Teahouse",
    "lang_name": "日本語",
    "notice": "新しい行を開始するにはEnterを押してください。Ctrl+Enterを押すか、ここをクリックしてメッセージを送信してください。",
    "online-peers": "オンラインユーザー: ",
    "peers-found": "ユーザーが見つかりました。チャットを開始します！",
    "posted-at": "投稿日時: ",
    "preview-init": "あなたのメッセージはここに表示されます。",
    "start": "Libp2pコアを起動しています...",
    "waiting": "Libp2pコアが起動しました。接続を待っています..."
  },
  "ko": {
    "channel": "/yutai-teahouse/ko",
    "title": "Yutai Teahouse",
    "lang_name": "한국어",
    "notice": "새 줄을 시작하려면 Enter를 누르십시오. Ctrl+Enter를 누르거나 여기를 클릭하여 메시지를 보내십시오.",
    "online-peers": "온라인 사용자: ",
    "peers-found": "사용자를 찾았습니다. 채팅을 시작하세요!",
    "posted-at": "게시 날짜: ",
    "preview-init": "귀하의 메시지가 여기에 표시됩니다.",
    "start": "Libp2p 코어를 시작합니다...",
    "waiting": "Libp2p 코어가 시작되었습니다. 연결을 기다리는 중입니다..."
  },
  "la": {
    "channel": "/yutai-teahouse/la",
    "title": "Yutai Teahouse",
    "lang_name": "Latina",
    "notice": "Pulsate Enter ut novam lineam incipere, pulsate Ctrl+Enter aut hic cliccate ut vestrum nuntium transmittere",
    "online-peers": "Usoribus in linea: ",
    "peers-found": "Usoribus inventis, colloquium incipite!",
    "posted-at": "Inseritur die: ",
    "preview-init": "Vestrum nuntium hic monstrabitur.",
    "start": "Libp2p core incipitur...",
    "waiting": "Libp2p core incipitur, coniunctiones exspectantes..."
  },
  "nl": {
    "channel": "/yutai-teahouse/nl",
    "title": "Yutai Teahouse",
    "lang_name": "Nederlands",
    "notice": "Druk op Enter om een nieuwe regel te beginnen, druk op Ctrl+Enter of klik hier om je bericht te versturen",
    "online-peers": "Online gebruikers: ",
    "peers-found": "Gebruikers gevonden, begin met chatten!",
    "posted-at": "Geplaatst op: ",
    "preview-init": "Je bericht wordt hier getoond.",
    "start": "Libp2p-kern wordt gestart...",
    "waiting": "Libp2p-kern gestart, wachtend op verbindingen..."
  },
  "no": {
    "channel": "/yutai-teahouse/no",
    "title": "Yutai Teahouse",
    "lang_name": "Norsk",
    "notice": "Trykk Enter for å starte en ny linje, trykk Ctrl+Enter eller klikk her for å sende meldingen din",
    "online-peers": "Brukere pålogget: ",
    "peers-found": "Brukere funnet, start å chatte!",
    "posted-at": "Postet: ",
    "preview-init": "Meldingen din vil bli vist her.",
    "start": "Starter Libp2p-kjernen...",
    "waiting": "Libp2p-kjernen startet, venter på tilkoblinger..."
  },
  "pl": {
    "channel": "/yutai-teahouse/pl",
    "title": "Yutai Teahouse",
    "lang_name": "Polski",
    "notice": "Naciśnij Enter, aby rozpocząć nową linię, naciśnij Ctrl+Enter lub kliknij tutaj, aby wysłać swoją wiadomość",
    "online-peers": "Użytkownicy online: ",
    "peers-found": "Znaleziono użytkowników, rozpocznij czat!",
    "posted-at": "Opublikowano: ",
    "preview-init": "Twoja wiadomość zostanie tutaj wyświetlona.",
    "start": "Uruchamianie rdzenia Libp2p...",
    "waiting": "Rdzeń Libp2p uruchomiony, oczekiwanie na połączenia..."
  },
  "pt-BR": {
    "channel": "/yutai-teahouse/pt-BR",
    "title": "Yutai Teahouse",
    "lang_name": "Português (Brasil)",
    "notice": "Pressione Enter para iniciar uma nova linha, pressione Ctrl+Enter ou clique aqui para enviar sua mensagem",
    "online-peers": "Usuários online: ",
    "peers-found": "Usuários encontrados, comece a conversar!",
    "posted-at": "Postado em: ",
    "preview-init": "Sua mensagem será mostrada aqui.",
    "start": "Iniciando o núcleo Libp2p...",
    "waiting": "Núcleo Libp2p iniciado, aguardando conexões..."
  },
  "pt-PT": {
    "channel": "/yutai-teahouse/pt-PT",
    "title": "Yutai Teahouse",
    "lang_name": "Português (Portugal)",
    "notice": "Pressione Enter para iniciar uma nova linha, pressione Ctrl+Enter ou clique aqui para enviar a sua mensagem",
    "online-peers": "Utilizadores online: ",
    "peers-found": "Utilizadores encontrados, comece a conversar!",
    "posted-at": "Publicado em: ",
    "preview-init": "A sua mensagem será mostrada aqui.",
    "start": "A iniciar o núcleo Libp2p...",
    "waiting": "Núcleo Libp2p iniciado, à espera de ligações..."
  },
  "ru": {
    "channel": "/yutai-teahouse/ru",
    "title": "Yutai Teahouse",
    "lang_name": "Русский",
    "notice": "Нажмите Enter, чтобы начать новую строку, нажмите Ctrl+Enter или нажмите здесь, чтобы отправить свое сообщение",
    "online-peers": "Пользователи онлайн: ",
    "peers-found": "Пользователи найдены, начните общаться!",
    "posted-at": "Опубликовано: ",
    "preview-init": "Ваше сообщение будет показано здесь.",
    "start": "Запуск ядра Libp2p...",
    "waiting": "Ядро Libp2p запущено, ожидание подключений..."
  },
  "th": {
    "channel": "/yutai-teahouse/th",
    "title": "Yutai Teahouse",
    "lang_name": "ภาษาไทย",
    "notice": "กด Enter เพื่อเริ่มบรรทัดใหม่, กด Ctrl+Enter หรือคลิกที่นี่เพื่อส่งข้อความของคุณ",
    "online-peers": "ผู้ใช้งานออนไลน์: ",
    "peers-found": "พบผู้ใช้งานเริ่มต้นการสนทนา!",
    "posted-at": "โพสต์เมื่อ: ",
    "preview-init": "ข้อความของคุณจะปรากฏที่นี่",
    "start": "กำลังเริ่มต้น Libp2p core...",
    "waiting": "Libp2p core เริ่มต้น, กำลังรอการเชื่อมต่อ..."
  },
  "tr": {
    "channel": "/yutai-teahouse/tr",
    "lang_name": "Türkçe",
    "notice": "Yeni bir satır başlatmak için Enter tuşuna basın, mesajınızı göndermek için Ctrl+Enter tuşlarına basın veya buraya tıklayın",
    "online-peers": "Çevrimiçi kullanıcılar: ",
    "peers-found": "Kullanıcılar bulundu, sohbete başlayın!",
    "posted-at": "Gönderildi: ",
    "preview-init": "Mesajınız burada gösterilecek.",
    "start": "Libp2p çekirdeği başlatılıyor...",
    "title": "Yutai Teahouse",
    "waiting": "Libp2p çekirdeği başlatıldı, bağlantılar bekleniyor..."
  },
  "ug": {
    "channel": "/yutai-teahouse/ug",
    "title": "Yutai Teahouse",
    "lang_name": "Uyƣurqə",
    "notice": "يېڭى قۇر ئۈچۈن Enter نى بېسىڭ ، Ctrl + Enter نى بېسىڭ ياكى بۇ يەرنى چېكىپ ئۇچۇر ئەۋەتىڭ",
    "online-peers": "توردىكى ئەزالار: ",
    "peers-found": "ئەزالار تېپىلدى، سۆھبەتكە بىرىڭ!",
    "posted-at": "يوللانغان ۋاقتى: ",
    "preview-init": "سىزنىڭ مەزمۇنىڭىز بۇ جايدا كۆرۈنىدۇ.",
    "start": "Libp2p باشلىنىش ...",
    "waiting": "Libp2p باشلىنىپ ئۇلىنىشنى ساقلاۋاتىدۇ. . ."
  },
  "zh-CN": {
    "channel": "/yutai-teahouse/zh-CN",
    "lang_name": "简体中文",
    "notice": "按回车键换行，按Ctrl+Enter或点击此处发送消息",
    "online-peers": "当前在线的节点：",
    "peers-found": "发现节点，开始聊天吧！",
    "posted-at": "发表于：",
    "preview-init": "这里将会显示你的消息预览。",
    "start": "正在启动 Libp2p 核心...",
    "title": "语台茶馆",
    "waiting": "Libp2p 核心已启动，正在等待节点连接..."
  },
  "zh-HK": {
    "channel": "/yutai-teahouse/zh-HK",
    "title": "Yutai Teahouse",
    "lang_name": "繁體中文 (香港)",
    "notice": "按 Enter 開始新行，按 Ctrl+Enter 或按此處發送您的訊息",
    "online-peers": "線上使用者：",
    "peers-found": "找到使用者，開始聊天！",
    "posted-at": "發佈於：",
    "preview-init": "您的訊息將會顯示在這裡。",
    "start": "啟動 Libp2p 核心...",
    "waiting": "Libp2p 核心已啟動，等待連線..."
  },
  "zh-TW": {
    "channel": "/yutai-teahouse/zh-TW",
    "title": "Yutai Teahouse",
    "lang_name": "繁體中文 (台灣)",
    "notice": "按 Enter 開始新行，按 Ctrl+Enter 或按此處發送您的訊息",
    "online-peers": "線上使用者：",
    "peers-found": "找到使用者，開始聊天！",
    "posted-at": "發佈於：",
    "preview-init": "您的訊息將會顯示在這裡。",
    "start": "啟動 Libp2p 核心...",
    "waiting": "Libp2p 核心已啟動，等待連線..."
  }
}
